cupp/__init__.py
cupp/__main__.py
cupp/functions.py
cupp/helper.py
cupp-1.3.3.dist-info/LICENSE
cupp-1.3.3.dist-info/METADATA
cupp-1.3.3.dist-info/WHEEL
cupp-1.3.3.dist-info/entry_points.txt
cupp-1.3.3.dist-info/top_level.txt
cupp-1.3.3.dist-info/RECORD
