Metadata-Version: 2.1
Name: cupp
Version: 1.3.3
Summary: Common User Password Profiler
Home-page: https://github.com/thehackersbrain/cupp
Author: Gaurav Raj
Author-email: techw803@gmail.com
License: MIT
Keywords: cupp,common user password profiler,wordlist,hacking,python,thehackersbrain,gauravraj
Platform: UNKNOWN
License-File: LICENSE
Requires-Dist: rich
